postie/__init__.py
postie/cli.py
postie/main.py
py_postie-0.10.dist-info/DESCRIPTION.rst
py_postie-0.10.dist-info/METADATA
py_postie-0.10.dist-info/RECORD
py_postie-0.10.dist-info/WHEEL
py_postie-0.10.dist-info/entry_points.txt
py_postie-0.10.dist-info/metadata.json
py_postie-0.10.dist-info/top_level.txt
